app/__init__.py
app/cli.py
app/main.py
app/config/__init__.py
app/config/settings.py
app/models/__init__.py
app/models/schemas.py
app/routers/__init__.py
app/routers/evaluate.py
app/services/__init__.py
app/services/evaluator.py
app/services/openai_client.py
app/utils/__init__.py
app/utils/markdown.py
huynk-1.0.4.dist-info/licenses/LICENSE
huynk-1.0.4.dist-info/METADATA
huynk-1.0.4.dist-info/WHEEL
huynk-1.0.4.dist-info/entry_points.txt
huynk-1.0.4.dist-info/top_level.txt
huynk-1.0.4.dist-info/RECORD
