Metadata-Version: 2.4
Name: huynk
Version: 1.0.4
Summary: Rule Evaluator API - He thong danh gia ho so bao hiem su dung AI
Author-email: HuyNK <huynk@example.com>
License-Expression: MIT
Project-URL: Homepage, https://github.com/huynk/huynk
Project-URL: Documentation, https://github.com/huynk/huynk#readme
Project-URL: Repository, https://github.com/huynk/huynk
Project-URL: Issues, https://github.com/huynk/huynk/issues
Keywords: insurance,evaluator,ai,openai,fastapi,rule-engine
Classifier: Development Status :: 4 - Beta
Classifier: Intended Audience :: Developers
Classifier: Operating System :: OS Independent
Classifier: Programming Language :: Python :: 3
Classifier: Programming Language :: Python :: 3.9
Classifier: Programming Language :: Python :: 3.10
Classifier: Programming Language :: Python :: 3.11
Classifier: Programming Language :: Python :: 3.12
Classifier: Topic :: Software Development :: Libraries :: Python Modules
Requires-Python: >=3.9
License-File: LICENSE
Requires-Dist: fastapi>=0.104.0
Requires-Dist: uvicorn>=0.24.0
Requires-Dist: python-multipart>=0.0.6
Requires-Dist: openai>=1.0.0
Requires-Dist: pandas>=2.0.0
Requires-Dist: openpyxl>=3.1.0
Requires-Dist: pydantic>=2.0.0
Requires-Dist: pydantic-settings>=2.0.0
Requires-Dist: python-dotenv>=1.0.0
Provides-Extra: dev
Requires-Dist: pytest>=7.0.0; extra == "dev"
Requires-Dist: pytest-asyncio>=0.21.0; extra == "dev"
Requires-Dist: httpx>=0.24.0; extra == "dev"
Dynamic: license-file
